{"columns":[{"kind":"Default","name":"Confidence","num_defaults":0,"num_rows":990},{"kind":"Default","name":"EventTimeDate","num_defaults":0,"num_rows":990},{"kind":"Default","name":"GLOBALEVENTID","num_defaults":0,"num_rows":990},{"kind":"Default","name":"InRawText","num_defaults":544,"num_rows":990},{"kind":"Default","name":"MentionDocLen","num_defaults":0,"num_rows":990},{"kind":"Default","name":"MentionDocTone","num_defaults":15,"num_rows":990},{"kind":"Default","name":"MentionIdentifier","num_defaults":0,"num_rows":990},{"kind":"Default","name":"MentionSourceName","num_defaults":0,"num_rows":990},{"kind":"Default","name":"MentionTimeDate","num_defaults":0,"num_rows":990},{"kind":"Default","name":"MentionType","num_defaults":0,"num_rows":990}],"types_serialization_versions":{"string":1},"version":1}